init/__init__.py
init/log.py
xiaohuohumax_test-1.0.0.dist-info/LICENSE
xiaohuohumax_test-1.0.0.dist-info/METADATA
xiaohuohumax_test-1.0.0.dist-info/WHEEL
xiaohuohumax_test-1.0.0.dist-info/top_level.txt
xiaohuohumax_test-1.0.0.dist-info/RECORD
