Metadata-Version: 2.1
Name: xiaohuohumax-test
Version: 1.0.0
Summary: no description
Author: xiaohuohumax
License: MIT
Keywords: xiaohuohumax,test
License-File: LICENSE
